[{"month":"2026-03","label":"March 2026","total_members":118,"avg_might":1520891701,"total_might":179465220759,"total_kills":40731690691,"total_might_gained":2064053122,"total_kills_gained":953947969,"snapshots_count":9,"members":[{"name":"oTheViking","date":"2026-03-20","rank":"RANK4","might":1946626634,"might_diff":0,"kills":2497846817,"kills_diff":0},{"name":"D A H L I A","date":"2026-03-31","rank":"RANK4","might":2307726967,"might_diff":-1201166,"kills":1466187561,"kills_diff":4855146},{"name":"Xo M oX","date":"2026-03-31","rank":"RANK3","might":1673612772,"might_diff":41899338,"kills":1410681195,"kills_diff":57506},{"name":"oThePanda","date":"2026-03-31","rank":"RANK3","might":1241339645,"might_diff":8734435,"kills":1307266543,"kills_diff":3972962},{"name":"xCrazy Busy","date":"2026-03-31","rank":"RANK3","might":1919760590,"might_diff":43751738,"kills":1259818610,"kills_diff":24374},{"name":"CaveBat","date":"2026-03-26","rank":"RANK1","might":1455309618,"might_diff":0,"kills":1238206352,"kills_diff":0},{"name":"dsgutrdghg","date":"2026-03-31","rank":"RANK4","might":2123794263,"might_diff":34298024,"kills":1069342221,"kills_diff":20053850},{"name":"Mr Yichen","date":"2026-03-31","rank":"RANK3","might":2293971101,"might_diff":-18906801,"kills":1004966196,"kills_diff":103683731},{"name":"luckycoin4","date":"2026-03-31","rank":"RANK3","might":1763215915,"might_diff":71498424,"kills":923264834,"kills_diff":16039091},{"name":"SK Genderuwo","date":"2026-03-31","rank":"RANK3","might":909447649,"might_diff":19155516,"kills":881512825,"kills_diff":4742898},{"name":"RAJNEEL SEN1","date":"2026-03-27","rank":"RANK1","might":2242746076,"might_diff":-16161997,"kills":849567465,"kills_diff":3238509},{"name":"DRAGON LH","date":"2026-03-31","rank":"RANK3","might":2196465038,"might_diff":8689837,"kills":801497255,"kills_diff":7233644},{"name":"Milk1104","date":"2026-03-31","rank":"RANK3","might":1459130398,"might_diff":27091825,"kills":787293092,"kills_diff":4211084},{"name":"Looking 4 me","date":"2026-03-31","rank":"RANK3","might":2182703255,"might_diff":22096116,"kills":719339503,"kills_diff":13647252},{"name":"Binzzz215","date":"2026-03-31","rank":"RANK3","might":1279332432,"might_diff":41687289,"kills":718496593,"kills_diff":5376290},{"name":"II Yumeko","date":"2026-03-31","rank":"RANK3","might":1448072847,"might_diff":1561908,"kills":688867673,"kills_diff":124507},{"name":"palmeiras87","date":"2026-03-31","rank":"RANK3","might":2013220382,"might_diff":50716896,"kills":663825192,"kills_diff":141289},{"name":"Luscop","date":"2026-03-31","rank":"RANK2","might":858465250,"might_diff":1975970,"kills":661343853,"kills_diff":609648},{"name":"TR11A03","date":"2026-03-31","rank":"RANK3","might":1524102269,"might_diff":5588126,"kills":579778524,"kills_diff":3085612},{"name":"Tieneko","date":"2026-03-31","rank":"RANK4","might":1710044630,"might_diff":-75596082,"kills":569802199,"kills_diff":274722959},{"name":"Arow63","date":"2026-03-31","rank":"RANK3","might":1470679844,"might_diff":50007900,"kills":564505259,"kills_diff":529886},{"name":"Ben2301","date":"2026-03-20","rank":"RANK4","might":1403646677,"might_diff":0,"kills":555143962,"kills_diff":0},{"name":"Izares","date":"2026-03-31","rank":"RANK3","might":2463728179,"might_diff":-2082519,"kills":538567634,"kills_diff":358518696},{"name":"Jieke0","date":"2026-03-31","rank":"RANK1","might":2802746681,"might_diff":-7284593,"kills":519781858,"kills_diff":12440796},{"name":"ZENIIX","date":"2026-03-31","rank":"RANK3","might":1851185648,"might_diff":7994516,"kills":511946139,"kills_diff":987111},{"name":"Sugoroku7","date":"2026-03-31","rank":"RANK4","might":2303963694,"might_diff":-4258584,"kills":481072635,"kills_diff":2310723},{"name":"OliveVN","date":"2026-03-30","rank":"RANK2","might":1913557685,"might_diff":-4798499,"kills":477455530,"kills_diff":1873656},{"name":"ordogfioka","date":"2026-03-31","rank":"RANK3","might":2451673730,"might_diff":7459675,"kills":470578922,"kills_diff":3588609},{"name":"RIGSSS","date":"2026-03-31","rank":"RANK4","might":1895794485,"might_diff":19273730,"kills":449446391,"kills_diff":2570283},{"name":"al tetra","date":"2026-03-31","rank":"RANK3","might":2276600647,"might_diff":-38013353,"kills":437151573,"kills_diff":13325302},{"name":"Devmani Sing","date":"2026-03-31","rank":"RANK2","might":1096603421,"might_diff":5098663,"kills":404875081,"kills_diff":89262},{"name":"1Shiz","date":"2026-03-31","rank":"RANK2","might":1881753891,"might_diff":8631110,"kills":384028251,"kills_diff":0},{"name":"IIEMPERYALII","date":"2026-03-20","rank":"RANK2","might":912472349,"might_diff":0,"kills":381466006,"kills_diff":0},{"name":"Darren69","date":"2026-03-31","rank":"RANK4","might":1628849985,"might_diff":29387147,"kills":374837716,"kills_diff":7676},{"name":"HOLALORD88","date":"2026-03-31","rank":"RANK3","might":1656388823,"might_diff":15680214,"kills":372419427,"kills_diff":0},{"name":"roman3265438","date":"2026-03-31","rank":"RANK3","might":2689592494,"might_diff":48393699,"kills":358167029,"kills_diff":4531837},{"name":"EMAN 1986","date":"2026-03-31","rank":"RANK3","might":1467714898,"might_diff":-28058421,"kills":355594123,"kills_diff":5486877},{"name":"vgk one","date":"2026-03-25","rank":"RANK2","might":1185892589,"might_diff":19909834,"kills":350100479,"kills_diff":0},{"name":"Rashford29","date":"2026-03-31","rank":"RANK3","might":880689351,"might_diff":15089672,"kills":342156297,"kills_diff":0},{"name":"Kim Tan","date":"2026-03-31","rank":"RANK2","might":1037364040,"might_diff":14037128,"kills":330463793,"kills_diff":204643},{"name":"Frank143","date":"2026-03-31","rank":"RANK3","might":1871098093,"might_diff":-10486399,"kills":328922383,"kills_diff":3979336},{"name":"Wibrahim","date":"2026-03-31","rank":"RANK3","might":1188187118,"might_diff":54218062,"kills":328426831,"kills_diff":6188422},{"name":"453798","date":"2026-03-31","rank":"RANK2","might":4471117883,"might_diff":148289191,"kills":320438642,"kills_diff":1575769},{"name":"Eltarii","date":"2026-03-31","rank":"RANK3","might":1697401659,"might_diff":-70349686,"kills":318066789,"kills_diff":1320839},{"name":"wimpyy","date":"2026-03-25","rank":"RANK2","might":1290053199,"might_diff":37218717,"kills":315275238,"kills_diff":0},{"name":"I Yumeko","date":"2026-03-31","rank":"RANK4","might":1625093015,"might_diff":30997687,"kills":315079835,"kills_diff":5291274},{"name":"PEDASKALI","date":"2026-03-31","rank":"RANK3","might":1513754344,"might_diff":5857230,"kills":314779753,"kills_diff":2603880},{"name":"Prischilla","date":"2026-03-31","rank":"RANK3","might":1674638048,"might_diff":17779509,"kills":313682923,"kills_diff":49988},{"name":"MASTER 1993","date":"2026-03-25","rank":"RANK2","might":1050059057,"might_diff":0,"kills":308018329,"kills_diff":0},{"name":"Le Clebard","date":"2026-03-25","rank":"RANK1","might":1704970905,"might_diff":0,"kills":301952589,"kills_diff":0},{"name":"katsu  katsu","date":"2026-03-31","rank":"RANK4","might":2380004498,"might_diff":-6192598,"kills":281438415,"kills_diff":3270036},{"name":"Cappyman","date":"2026-03-31","rank":"RANK3","might":1573177713,"might_diff":339947,"kills":266442306,"kills_diff":633610},{"name":"SICILYMAN","date":"2026-03-31","rank":"RANK3","might":1068903964,"might_diff":14343154,"kills":263710388,"kills_diff":87769},{"name":"Jjoyboyy","date":"2026-03-31","rank":"RANK2","might":1231403472,"might_diff":7253044,"kills":259598196,"kills_diff":2348858},{"name":"KollerGK","date":"2026-03-31","rank":"RANK3","might":1464088068,"might_diff":20837742,"kills":248988045,"kills_diff":0},{"name":"Charlyx1x","date":"2026-03-31","rank":"RANK2","might":1211440710,"might_diff":15254340,"kills":244234653,"kills_diff":0},{"name":"Chen Pei Xin","date":"2026-03-20","rank":"RANK3","might":2013909177,"might_diff":0,"kills":240992229,"kills_diff":0},{"name":"CHiLL2NiGHT","date":"2026-03-31","rank":"RANK4","might":1740937243,"might_diff":24345527,"kills":238667065,"kills_diff":835468},{"name":"Duc Pham","date":"2026-03-31","rank":"RANK2","might":1717135333,"might_diff":25469236,"kills":231389036,"kills_diff":5106565},{"name":"Naive ovo","date":"2026-03-31","rank":"RANK4","might":1927236662,"might_diff":15880052,"kills":228020814,"kills_diff":30001},{"name":"HuuHanh","date":"2026-03-20","rank":"RANK2","might":1362681870,"might_diff":0,"kills":224710986,"kills_diff":0},{"name":"160600","date":"2026-03-31","rank":"RANK2","might":1419463959,"might_diff":10546481,"kills":211461220,"kills_diff":0},{"name":"TR Reyald","date":"2026-03-30","rank":"RANK1","might":881880995,"might_diff":20066758,"kills":206982944,"kills_diff":5044901},{"name":"Itachi285","date":"2026-03-30","rank":"RANK3","might":1171578461,"might_diff":38790178,"kills":206979951,"kills_diff":1052478},{"name":"Valentex","date":"2026-03-30","rank":"RANK2","might":1812526402,"might_diff":3133985,"kills":203638676,"kills_diff":163994},{"name":"I  Nagato II","date":"2026-03-23","rank":"RANK2","might":1189371307,"might_diff":178080,"kills":198598860,"kills_diff":0},{"name":"OMeRo77","date":"2026-03-31","rank":"RANK1","might":1280393795,"might_diff":-4317974,"kills":191548605,"kills_diff":544756},{"name":"Mahesh 1433","date":"2026-03-31","rank":"RANK3","might":1502423026,"might_diff":30345695,"kills":183376967,"kills_diff":0},{"name":"kathLeen07","date":"2026-03-31","rank":"RANK3","might":1692657717,"might_diff":308397276,"kills":180515883,"kills_diff":94405},{"name":"CatFishx","date":"2026-03-31","rank":"RANK3","might":1107465897,"might_diff":6309201,"kills":177658406,"kills_diff":1980760},{"name":"Tio Vegeta","date":"2026-03-31","rank":"RANK3","might":1082268949,"might_diff":-14100830,"kills":171570008,"kills_diff":1875561},{"name":"venom 005","date":"2026-03-31","rank":"RANK3","might":879636831,"might_diff":16905113,"kills":163631821,"kills_diff":782574},{"name":"Eagle10","date":"2026-03-31","rank":"RANK3","might":1032821226,"might_diff":21218681,"kills":160142045,"kills_diff":321252},{"name":"gdooo","date":"2026-03-31","rank":"RANK3","might":2806893190,"might_diff":14756118,"kills":159265132,"kills_diff":681900},{"name":"Ry0hei","date":"2026-03-23","rank":"RANK2","might":964748566,"might_diff":2438653,"kills":155213252,"kills_diff":0},{"name":"el viejo","date":"2026-03-31","rank":"RANK2","might":1117087620,"might_diff":94998982,"kills":152064867,"kills_diff":858233},{"name":"milaros","date":"2026-03-31","rank":"RANK3","might":2027410786,"might_diff":27629379,"kills":151900287,"kills_diff":146070},{"name":"Vladimir G","date":"2026-03-31","rank":"RANK1","might":1326029586,"might_diff":2078244,"kills":151667900,"kills_diff":12760},{"name":"Sieu348","date":"2026-03-31","rank":"RANK3","might":1444227863,"might_diff":-21700,"kills":150309608,"kills_diff":1459370},{"name":"Armannd0","date":"2026-03-31","rank":"RANK3","might":1352237248,"might_diff":19667891,"kills":145935917,"kills_diff":398669},{"name":"OliveiraPY","date":"2026-03-31","rank":"RANK3","might":1287767832,"might_diff":-18179174,"kills":143051941,"kills_diff":4421533},{"name":"Black Ichigo","date":"2026-03-31","rank":"RANK2","might":1558795309,"might_diff":18805797,"kills":133897096,"kills_diff":0},{"name":"iOoNe","date":"2026-03-31","rank":"RANK2","might":1344419589,"might_diff":5224570,"kills":131683594,"kills_diff":270107},{"name":"Clayton V","date":"2026-03-20","rank":"RANK2","might":1503745891,"might_diff":0,"kills":130782354,"kills_diff":0},{"name":"EnchanterTTT","date":"2026-03-31","rank":"RANK3","might":2164814345,"might_diff":7290062,"kills":127914788,"kills_diff":2269394},{"name":"JJZeusJJ","date":"2026-03-23","rank":"RANK2","might":1150843041,"might_diff":0,"kills":127567528,"kills_diff":0},{"name":"Arjan Don","date":"2026-03-31","rank":"RANK3","might":578528098,"might_diff":97874659,"kills":121584790,"kills_diff":1854},{"name":"Bi9 99","date":"2026-03-31","rank":"RANK3","might":1531239439,"might_diff":41269638,"kills":118837721,"kills_diff":91458},{"name":"MorcyJhon","date":"2026-03-31","rank":"RANK3","might":1013377614,"might_diff":14659887,"kills":118691844,"kills_diff":3812846},{"name":"A u ro ra","date":"2026-03-31","rank":"RANK2","might":1038487075,"might_diff":9264550,"kills":116510265,"kills_diff":11},{"name":"FLORECITA06","date":"2026-03-23","rank":"RANK2","might":1297785149,"might_diff":0,"kills":115930901,"kills_diff":0},{"name":"Chocoflan1","date":"2026-03-31","rank":"RANK3","might":1350347728,"might_diff":36212599,"kills":115168724,"kills_diff":0},{"name":"Ninhbinh","date":"2026-03-31","rank":"RANK3","might":1101364134,"might_diff":38600848,"kills":112636619,"kills_diff":1753406},{"name":"ROSEWALL X","date":"2026-03-31","rank":"RANK2","might":1327822194,"might_diff":15960421,"kills":111911013,"kills_diff":105364},{"name":"German Areta","date":"2026-03-31","rank":"RANK4","might":1411631775,"might_diff":-492666,"kills":99844086,"kills_diff":2098728},{"name":"Beeeast","date":"2026-03-31","rank":"RANK3","might":2644578002,"might_diff":12025396,"kills":96929752,"kills_diff":5765687},{"name":"egao","date":"2026-03-31","rank":"RANK3","might":2560317172,"might_diff":39350321,"kills":87496314,"kills_diff":4596646},{"name":"Nohave a gun","date":"2026-03-31","rank":"RANK3","might":958374690,"might_diff":17292923,"kills":82697433,"kills_diff":0},{"name":"TheKing 6789","date":"2026-03-20","rank":"RANK3","might":1104176951,"might_diff":0,"kills":75836719,"kills_diff":0},{"name":"Rallito 01","date":"2026-03-31","rank":"RANK3","might":2097912076,"might_diff":22561391,"kills":72157601,"kills_diff":0},{"name":"Tha Wences","date":"2026-03-31","rank":"RANK3","might":1388684510,"might_diff":10013556,"kills":65355560,"kills_diff":0},{"name":"Gato Plus","date":"2026-03-31","rank":"RANK1","might":1203846259,"might_diff":13095837,"kills":58741277,"kills_diff":396120},{"name":"ELYSINA","date":"2026-03-23","rank":"RANK2","might":1166778697,"might_diff":355357,"kills":55206349,"kills_diff":0},{"name":"KingAtli","date":"2026-03-31","rank":"RANK2","might":1137472506,"might_diff":2276668,"kills":48730865,"kills_diff":153040},{"name":"Golden Boy19","date":"2026-03-20","rank":"RANK3","might":987907352,"might_diff":0,"kills":44532289,"kills_diff":0},{"name":"Nekoarerugi","date":"2026-03-31","rank":"RANK2","might":1058261291,"might_diff":55898947,"kills":40187340,"kills_diff":854558},{"name":"NEWBIE two","date":"2026-03-23","rank":"RANK1","might":1131141672,"might_diff":0,"kills":39676783,"kills_diff":0},{"name":"AxelMax1","date":"2026-03-31","rank":"RANK3","might":644115363,"might_diff":12081117,"kills":32236479,"kills_diff":1933},{"name":"kiiiiiiton","date":"2026-03-31","rank":"RANK3","might":2683886913,"might_diff":16665052,"kills":26578691,"kills_diff":919137},{"name":"AHMETCY","date":"2026-03-31","rank":"RANK3","might":924168559,"might_diff":123416974,"kills":19456492,"kills_diff":1198500},{"name":"xgalax","date":"2026-03-31","rank":"RANK3","might":1195208425,"might_diff":15689332,"kills":17534377,"kills_diff":3512243},{"name":"MoonOrchid","date":"2026-03-23","rank":"RANK1","might":843255069,"might_diff":561812,"kills":16520804,"kills_diff":0},{"name":"Misaaa4","date":"2026-03-31","rank":"RANK3","might":978035410,"might_diff":27609049,"kills":15703223,"kills_diff":0},{"name":"pr0fessor1","date":"2026-03-31","rank":"RANK2","might":645289962,"might_diff":18129231,"kills":12288121,"kills_diff":668759},{"name":"Sanko925","date":"2026-03-20","rank":"RANK3","might":882168469,"might_diff":0,"kills":11851287,"kills_diff":0},{"name":"Darren69 Bnk","date":"2026-03-31","rank":"RANK1","might":434839848,"might_diff":34316793,"kills":9750592,"kills_diff":0},{"name":"Taurus8","date":"2026-03-31","rank":"RANK2","might":1086062402,"might_diff":14913815,"kills":2116634,"kills_diff":31438},{"name":"abankbro","date":"2026-03-31","rank":"RANK5","might":359367651,"might_diff":7886679,"kills":132043,"kills_diff":0}]},{"month":"2026-04","label":"April 2026","total_members":137,"avg_might":1408049174,"total_might":192902736949,"total_kills":46447143588,"total_might_gained":1530350180,"total_kills_gained":629678454,"snapshots_count":14,"members":[{"name":"Ahiaa","date":"2026-04-02","rank":"RANK1","might":2181109672,"might_diff":0,"kills":1955809117,"kills_diff":0},{"name":"Lord ARJ","date":"2026-04-04","rank":"RANK4","might":1695303147,"might_diff":0,"kills":1507900524,"kills_diff":0},{"name":"D A H L I A","date":"2026-04-14","rank":"RANK4","might":2322589171,"might_diff":13602586,"kills":1468035312,"kills_diff":1847751},{"name":"Xo M oX","date":"2026-04-14","rank":"RANK3","might":1721041375,"might_diff":43785518,"kills":1410961148,"kills_diff":279953},{"name":"darkrealm","date":"2026-04-04","rank":"RANK1","might":2134528068,"might_diff":-12489308,"kills":1344012950,"kills_diff":0},{"name":"oThePanda","date":"2026-04-14","rank":"RANK3","might":1291050180,"might_diff":45506671,"kills":1313263579,"kills_diff":5247071},{"name":"xCrazy Busy","date":"2026-04-14","rank":"RANK3","might":1956482338,"might_diff":33258154,"kills":1263665018,"kills_diff":3846408},{"name":"Boss Pro VN","date":"2026-04-14","rank":"RANK2","might":1156868575,"might_diff":11836130,"kills":1210522131,"kills_diff":361107},{"name":"dsgutrdghg","date":"2026-04-14","rank":"RANK4","might":2054096046,"might_diff":-71467422,"kills":1122974261,"kills_diff":53632040},{"name":"Mr Yichen","date":"2026-04-14","rank":"RANK3","might":2317572210,"might_diff":4356732,"kills":1005734160,"kills_diff":767964},{"name":"hyacinthia","date":"2026-04-02","rank":"RANK1","might":1156220874,"might_diff":0,"kills":972878549,"kills_diff":0},{"name":"luckycoin4","date":"2026-04-14","rank":"RANK3","might":1844218284,"might_diff":79147058,"kills":944589822,"kills_diff":21265502},{"name":"SK Genderuwo","date":"2026-04-14","rank":"RANK3","might":938117201,"might_diff":25198611,"kills":894461957,"kills_diff":12949132},{"name":"DRAGON LH","date":"2026-04-14","rank":"RANK3","might":2223324107,"might_diff":24400941,"kills":809496723,"kills_diff":7368975},{"name":"Milk1104","date":"2026-04-14","rank":"RANK3","might":1483373183,"might_diff":19703782,"kills":801405764,"kills_diff":14112672},{"name":"Looking 4 me","date":"2026-04-10","rank":"RANK1","might":2211338512,"might_diff":24824549,"kills":730187374,"kills_diff":9937997},{"name":"Binzzz215","date":"2026-04-14","rank":"RANK3","might":1362480099,"might_diff":80526411,"kills":727793367,"kills_diff":9296774},{"name":"MR QUNTULL","date":"2026-04-12","rank":"RANK1","might":1719773131,"might_diff":-2566604,"kills":693072463,"kills_diff":2489533},{"name":"II Yumeko","date":"2026-04-14","rank":"RANK3","might":1445446077,"might_diff":-2626770,"kills":689801040,"kills_diff":933367},{"name":"palmeiras87","date":"2026-04-14","rank":"RANK3","might":2053017322,"might_diff":36624380,"kills":669717800,"kills_diff":5892608},{"name":"Luscop","date":"2026-04-14","rank":"RANK2","might":876615110,"might_diff":9418792,"kills":665837374,"kills_diff":4493521},{"name":"fiona25","date":"2026-04-02","rank":"RANK1","might":1554570975,"might_diff":0,"kills":647399120,"kills_diff":0},{"name":"Tieneko","date":"2026-04-14","rank":"RANK4","might":1629087849,"might_diff":-71107897,"kills":624292467,"kills_diff":54490268},{"name":"TR11A03","date":"2026-04-14","rank":"RANK3","might":1505133413,"might_diff":-40401583,"kills":590590735,"kills_diff":10812211},{"name":"Tuyen1a","date":"2026-04-04","rank":"RANK1","might":1365470264,"might_diff":0,"kills":581268668,"kills_diff":0},{"name":"Arow63","date":"2026-04-14","rank":"RANK3","might":1504119452,"might_diff":27120160,"kills":565900838,"kills_diff":1395579},{"name":"Cards","date":"2026-04-04","rank":"RANK1","might":3695211172,"might_diff":0,"kills":562223300,"kills_diff":0},{"name":"Izares","date":"2026-04-14","rank":"RANK3","might":2412137175,"might_diff":-52161208,"kills":548314286,"kills_diff":9746652},{"name":"ZENIIX","date":"2026-04-14","rank":"RANK3","might":1881117554,"might_diff":7217800,"kills":528719502,"kills_diff":16773363},{"name":"Jieke0","date":"2026-04-14","rank":"RANK3","might":2864574372,"might_diff":61729691,"kills":523274150,"kills_diff":3492292},{"name":"xGENERAL","date":"2026-04-04","rank":"RANK1","might":1917097643,"might_diff":0,"kills":506068199,"kills_diff":0},{"name":"Sugoroku7","date":"2026-04-14","rank":"RANK4","might":2271153848,"might_diff":-32932379,"kills":494582206,"kills_diff":13474383},{"name":"ordogfioka","date":"2026-04-14","rank":"RANK3","might":2478840598,"might_diff":25835903,"kills":483716276,"kills_diff":13137354},{"name":"al tetra","date":"2026-04-14","rank":"RANK3","might":2310932169,"might_diff":-5767724,"kills":483560559,"kills_diff":46408986},{"name":"OliveVN","date":"2026-04-03","rank":"RANK2","might":1923468521,"might_diff":1351487,"kills":477455530,"kills_diff":0},{"name":"RIGSSS","date":"2026-04-14","rank":"RANK4","might":1904954574,"might_diff":9160089,"kills":462430297,"kills_diff":12983906},{"name":"AG67Dang1999","date":"2026-04-02","rank":"RANK1","might":870671884,"might_diff":0,"kills":436139962,"kills_diff":0},{"name":"Devmani Sing","date":"2026-04-14","rank":"RANK3","might":1092164630,"might_diff":-4471511,"kills":407190002,"kills_diff":2314921},{"name":"Wibrahim","date":"2026-04-14","rank":"RANK3","might":1343247232,"might_diff":139440398,"kills":387616006,"kills_diff":59189175},{"name":"1Shiz","date":"2026-04-14","rank":"RANK2","might":1885403204,"might_diff":3133184,"kills":384028251,"kills_diff":0},{"name":"Darren69","date":"2026-04-14","rank":"RANK4","might":1692600918,"might_diff":57731292,"kills":374837716,"kills_diff":0},{"name":"HOLALORD88","date":"2026-04-14","rank":"RANK3","might":1682934721,"might_diff":18800422,"kills":373876093,"kills_diff":1456666},{"name":"EMAN 1986","date":"2026-04-14","rank":"RANK3","might":1515677851,"might_diff":45297981,"kills":359221426,"kills_diff":3627303},{"name":"roman3265438","date":"2026-04-04","rank":"RANK3","might":2712951917,"might_diff":17961107,"kills":358168784,"kills_diff":1755},{"name":"Rashford29","date":"2026-04-11","rank":"RANK3","might":891743945,"might_diff":10161506,"kills":342156297,"kills_diff":0},{"name":"Eltarii","date":"2026-04-14","rank":"RANK3","might":1709992441,"might_diff":5664130,"kills":336708744,"kills_diff":18641955},{"name":"Frank143","date":"2026-04-14","rank":"RANK3","might":1890492536,"might_diff":13640551,"kills":333735231,"kills_diff":4812848},{"name":"Kim Tan","date":"2026-04-14","rank":"RANK2","might":1056694364,"might_diff":18556810,"kills":330660827,"kills_diff":197034},{"name":"I Yumeko","date":"2026-04-14","rank":"RANK4","might":1651492154,"might_diff":26353021,"kills":329272223,"kills_diff":14192388},{"name":"453798","date":"2026-04-14","rank":"RANK2","might":4750570590,"might_diff":256108505,"kills":326159730,"kills_diff":5721088},{"name":"PEDASKALI","date":"2026-04-14","rank":"RANK3","might":1490065547,"might_diff":-24344455,"kills":323159370,"kills_diff":8379617},{"name":"Realmatters","date":"2026-04-08","rank":"RANK2","might":1498883208,"might_diff":41748719,"kills":317747930,"kills_diff":0},{"name":"Prischilla","date":"2026-04-14","rank":"RANK3","might":1702359591,"might_diff":27323098,"kills":313763525,"kills_diff":80602},{"name":"katsu  katsu","date":"2026-04-14","rank":"RANK4","might":2388542702,"might_diff":8294108,"kills":282673848,"kills_diff":1235433},{"name":"Cappyman","date":"2026-04-14","rank":"RANK3","might":1600629739,"might_diff":32341146,"kills":266811691,"kills_diff":369385},{"name":"Jjoyboyy","date":"2026-04-14","rank":"RANK2","might":1210134810,"might_diff":-14161953,"kills":266543850,"kills_diff":6945654},{"name":"CHiLL2NiGHT","date":"2026-04-14","rank":"RANK4","might":1682805018,"might_diff":-59300174,"kills":265437844,"kills_diff":26770779},{"name":"SICILYMAN","date":"2026-04-14","rank":"RANK3","might":1075353316,"might_diff":6172239,"kills":265282488,"kills_diff":1572100},{"name":"KollerGK","date":"2026-04-14","rank":"RANK3","might":1480864866,"might_diff":16375858,"kills":249309723,"kills_diff":321678},{"name":"Charlyx1x","date":"2026-04-07","rank":"RANK1","might":1214775434,"might_diff":417451306,"kills":244234653,"kills_diff":0},{"name":"Duc Pham","date":"2026-04-13","rank":"RANK3","might":1733106493,"might_diff":10462851,"kills":234906017,"kills_diff":3516981},{"name":"XKaito KidX","date":"2026-04-03","rank":"RANK1","might":773417166,"might_diff":0,"kills":233965147,"kills_diff":0},{"name":"Chee lengx","date":"2026-04-14","rank":"RANK1","might":1091132162,"might_diff":0,"kills":232038732,"kills_diff":0},{"name":"Naive ovo","date":"2026-04-14","rank":"RANK4","might":1953983056,"might_diff":25912442,"kills":229058677,"kills_diff":1037863},{"name":"100 0000000","date":"2026-04-04","rank":"RANK1","might":1410832569,"might_diff":0,"kills":215558937,"kills_diff":0},{"name":"Itachi285","date":"2026-04-14","rank":"RANK3","might":1168352835,"might_diff":-4378847,"kills":212470053,"kills_diff":4961940},{"name":"160600","date":"2026-04-10","rank":"RANK2","might":1425227659,"might_diff":5123700,"kills":211461220,"kills_diff":0},{"name":"bablo bablo","date":"2026-04-03","rank":"RANK1","might":747395723,"might_diff":0,"kills":210137113,"kills_diff":0},{"name":"TR Reyald","date":"2026-04-01","rank":"RANK1","might":837611843,"might_diff":0,"kills":206982944,"kills_diff":0},{"name":"0lobo01","date":"2026-04-12","rank":"RANK1","might":1183200201,"might_diff":0,"kills":206387127,"kills_diff":0},{"name":"Valentex","date":"2026-04-14","rank":"RANK2","might":1828782984,"might_diff":10984800,"kills":205440729,"kills_diff":1802053},{"name":"OMeRo77","date":"2026-04-14","rank":"RANK3","might":1297381209,"might_diff":19975194,"kills":194416773,"kills_diff":2868168},{"name":"CatFishx","date":"2026-04-14","rank":"RANK3","might":1122446373,"might_diff":12807184,"kills":186911147,"kills_diff":9252741},{"name":"Brenchong93","date":"2026-04-07","rank":"RANK1","might":754331070,"might_diff":449986,"kills":184823872,"kills_diff":0},{"name":"Mahesh 1433","date":"2026-04-14","rank":"RANK3","might":1520971653,"might_diff":15890257,"kills":183785569,"kills_diff":408602},{"name":"kathLeen07","date":"2026-04-14","rank":"RANK3","might":1722762608,"might_diff":29747219,"kills":180957607,"kills_diff":441724},{"name":"Tio Vegeta","date":"2026-04-14","rank":"RANK3","might":1089451734,"might_diff":5134803,"kills":172732939,"kills_diff":1162931},{"name":"DBCz","date":"2026-04-14","rank":"RANK2","might":1104937820,"might_diff":-23804783,"kills":168730098,"kills_diff":4565390},{"name":"crazy2230","date":"2026-04-02","rank":"RANK1","might":731856074,"might_diff":0,"kills":168335773,"kills_diff":0},{"name":"venom 005","date":"2026-04-14","rank":"RANK3","might":908684303,"might_diff":25283957,"kills":164380139,"kills_diff":748318},{"name":"Naen2267","date":"2026-04-02","rank":"RANK1","might":912969591,"might_diff":0,"kills":162043984,"kills_diff":0},{"name":"Eagle10","date":"2026-04-03","rank":"RANK3","might":1033058286,"might_diff":237060,"kills":160318287,"kills_diff":176242},{"name":"milaros","date":"2026-04-14","rank":"RANK3","might":2042004471,"might_diff":14593685,"kills":160023795,"kills_diff":8123508},{"name":"gdooo","date":"2026-04-14","rank":"RANK3","might":2855932082,"might_diff":45320600,"kills":159349133,"kills_diff":84001},{"name":"el viejo","date":"2026-04-14","rank":"RANK2","might":1312690920,"might_diff":172489150,"kills":156864354,"kills_diff":4799487},{"name":"Armannd0","date":"2026-04-14","rank":"RANK3","might":1101788711,"might_diff":-250657833,"kills":154596625,"kills_diff":8660708},{"name":"Vladimir G","date":"2026-04-14","rank":"RANK2","might":1361501250,"might_diff":29973900,"kills":154234902,"kills_diff":2567002},{"name":"Sieu348","date":"2026-04-14","rank":"RANK3","might":1456319646,"might_diff":17340050,"kills":153521565,"kills_diff":3211957},{"name":"OSKR07","date":"2026-04-04","rank":"RANK1","might":1109081228,"might_diff":0,"kills":147612005,"kills_diff":0},{"name":"OliveiraPY","date":"2026-04-14","rank":"RANK3","might":1305998335,"might_diff":7744476,"kills":145827560,"kills_diff":2775619},{"name":"Black Ichigo","date":"2026-04-14","rank":"RANK2","might":1640635140,"might_diff":58480347,"kills":133898096,"kills_diff":1000},{"name":"iOoNe","date":"2026-04-14","rank":"RANK2","might":1355662143,"might_diff":22489818,"kills":133636007,"kills_diff":1952413},{"name":"Bi9 99","date":"2026-04-14","rank":"RANK3","might":1537833526,"might_diff":2940829,"kills":129437360,"kills_diff":10599639},{"name":"EnchanterTTT","date":"2026-04-14","rank":"RANK3","might":2137028530,"might_diff":-28481223,"kills":128210236,"kills_diff":295448},{"name":"Arjan Don","date":"2026-04-14","rank":"RANK3","might":624675102,"might_diff":30046364,"kills":123406544,"kills_diff":1821754},{"name":"XBLACKBERRY1","date":"2026-04-11","rank":"RANK3","might":1352307679,"might_diff":14483534,"kills":121173643,"kills_diff":0},{"name":"MorcyJhon","date":"2026-04-14","rank":"RANK3","might":1032385095,"might_diff":12453071,"kills":121092370,"kills_diff":2400526},{"name":"Chocoflan1","date":"2026-04-14","rank":"RANK3","might":1383035986,"might_diff":32005782,"kills":117319515,"kills_diff":2150791},{"name":"A u ro ra","date":"2026-04-14","rank":"RANK2","might":1048450925,"might_diff":9591885,"kills":116550684,"kills_diff":40419},{"name":"PapaLobo","date":"2026-04-14","rank":"RANK2","might":1279227102,"might_diff":16810534,"kills":113699482,"kills_diff":538393},{"name":"Ninhbinh","date":"2026-04-05","rank":"RANK3","might":1115256458,"might_diff":44187200,"kills":112818436,"kills_diff":181817},{"name":"Xx HUNTER","date":"2026-04-14","rank":"RANK2","might":1409183601,"might_diff":8659776,"kills":112560922,"kills_diff":0},{"name":"ROSEWALL X","date":"2026-04-10","rank":"RANK2","might":1338450253,"might_diff":6688717,"kills":111911013,"kills_diff":0},{"name":"Beeeast","date":"2026-04-14","rank":"RANK3","might":2695331236,"might_diff":49737531,"kills":110913115,"kills_diff":13983363},{"name":"GRI  ANKIT","date":"2026-04-14","rank":"RANK2","might":1140216887,"might_diff":2184332,"kills":109379857,"kills_diff":0},{"name":"German Areta","date":"2026-04-14","rank":"RANK4","might":890331718,"might_diff":-519530157,"kills":102816198,"kills_diff":2972112},{"name":"egao","date":"2026-04-14","rank":"RANK3","might":2600312761,"might_diff":27940058,"kills":96745050,"kills_diff":9248736},{"name":"Nohave a gun","date":"2026-04-14","rank":"RANK3","might":985986140,"might_diff":25012570,"kills":83141781,"kills_diff":444348},{"name":"Rallito 01","date":"2026-04-06","rank":"RANK3","might":2120452690,"might_diff":14864103,"kills":72157601,"kills_diff":0},{"name":"TOB1 36","date":"2026-04-02","rank":"RANK1","might":949774353,"might_diff":0,"kills":68267296,"kills_diff":0},{"name":"Tha Wences","date":"2026-04-08","rank":"RANK3","might":1410154093,"might_diff":17373223,"kills":65355560,"kills_diff":0},{"name":"Gato Plus","date":"2026-04-14","rank":"RANK3","might":1237776166,"might_diff":31616593,"kills":59047541,"kills_diff":306264},{"name":"dimitripayet","date":"2026-04-04","rank":"RANK1","might":1054091386,"might_diff":0,"kills":52907301,"kills_diff":0},{"name":"KingAtli","date":"2026-04-14","rank":"RANK2","might":1122555348,"might_diff":-15110157,"kills":52210198,"kills_diff":3479333},{"name":"TatsunamiDA","date":"2026-04-04","rank":"RANK1","might":547664243,"might_diff":0,"kills":45535655,"kills_diff":0},{"name":"Nekoarerugi","date":"2026-04-14","rank":"RANK3","might":1081823831,"might_diff":26943794,"kills":40523895,"kills_diff":336555},{"name":"AHMETCY","date":"2026-04-14","rank":"RANK3","might":900100674,"might_diff":-45904025,"kills":33525576,"kills_diff":14069084},{"name":"AxelMax1","date":"2026-04-14","rank":"RANK3","might":651702808,"might_diff":7605533,"kills":32244703,"kills_diff":8224},{"name":"xgalax","date":"2026-04-14","rank":"RANK3","might":1249900575,"might_diff":51992073,"kills":27615693,"kills_diff":10081316},{"name":"kiiiiiiton","date":"2026-04-14","rank":"RANK3","might":2699543302,"might_diff":14775059,"kills":26620801,"kills_diff":42110},{"name":"Misaaa4","date":"2026-04-14","rank":"RANK3","might":984280577,"might_diff":6245167,"kills":15703223,"kills_diff":0},{"name":"pr0fessor1","date":"2026-04-14","rank":"RANK3","might":667131602,"might_diff":21197451,"kills":12345362,"kills_diff":57241},{"name":"Ashi kyoto","date":"2026-04-11","rank":"RANK2","might":1005494764,"might_diff":-8339879,"kills":11822907,"kills_diff":234583},{"name":"Darren69 Bnk","date":"2026-04-14","rank":"RANK1","might":463976438,"might_diff":28342060,"kills":9750592,"kills_diff":0},{"name":"Itachiiii2","date":"2026-04-12","rank":"RANK1","might":100088575,"might_diff":199336,"kills":7138757,"kills_diff":0},{"name":"5P1N","date":"2026-04-14","rank":"RANK1","might":335021444,"might_diff":1998,"kills":5826580,"kills_diff":0},{"name":"Rainy0o0","date":"2026-04-08","rank":"RANK1","might":421632688,"might_diff":0,"kills":3716504,"kills_diff":0},{"name":"Diara Fealme","date":"2026-04-11","rank":"RANK1","might":53150682,"might_diff":0,"kills":2997103,"kills_diff":0},{"name":"Tliha Wlail","date":"2026-04-07","rank":"RANK1","might":52369177,"might_diff":0,"kills":2438364,"kills_diff":0},{"name":"Feay Pencri","date":"2026-04-07","rank":"RANK1","might":53026732,"might_diff":0,"kills":2390910,"kills_diff":0},{"name":"Taurus8","date":"2026-04-14","rank":"RANK2","might":1127660101,"might_diff":38689905,"kills":2116634,"kills_diff":0},{"name":"Ronla Elies","date":"2026-04-11","rank":"RANK1","might":52403713,"might_diff":0,"kills":394656,"kills_diff":0},{"name":"Hilad Jade","date":"2026-04-11","rank":"RANK1","might":53339726,"might_diff":0,"kills":375110,"kills_diff":0},{"name":"Trits Kevni","date":"2026-04-11","rank":"RANK1","might":54305199,"might_diff":0,"kills":374349,"kills_diff":0},{"name":"Izares2","date":"2026-04-14","rank":"RANK1","might":99557477,"might_diff":39000,"kills":370468,"kills_diff":0},{"name":"abankbro","date":"2026-04-14","rank":"RANK5","might":359399856,"might_diff":33285,"kills":132043,"kills_diff":0},{"name":"miniDAHLIA","date":"2026-04-12","rank":"RANK1","might":77351513,"might_diff":93004,"kills":2294,"kills_diff":0}]}]